opseestools/Lib_frag.py
opseestools/__init__.py
opseestools/analisis.py
opseestools/analisis3D.py
opseestools/utilidades.py
opseestools-1.20.dist-info/METADATA
opseestools-1.20.dist-info/WHEEL
opseestools-1.20.dist-info/top_level.txt
opseestools-1.20.dist-info/RECORD
