Metadata-Version: 2.1
Name: opseestools
Version: 1.20
Summary: A collection of OpenSeesPy routines for performing several types of analyses and other tools
Home-page: https://github.com/odarroyo/opseestools
Author: Orlando Arroyo
Author-email: orlando.arroyo@uis.edu.co
License: LICENSE
Requires-Python: >=3.9
Requires-Dist: openseespy >=3.5
Requires-Dist: matplotlib
Requires-Dist: numpy
Requires-Dist: scipy >=1.11
Requires-Dist: pandas >=2.0
Requires-Dist: opstool
